streams_optimization/__init__.py
streams_optimization/cast_unicode_to_str.py
streams_optimization/data.py
streams_optimization/model.py
streams_optimization/utils.py
streams_optimization/write_streaming_scheme.py
streams_optimization/tests/__init__.py
streams_optimization/tests/test_compute_T_score.py
streams_optimization/tests/test_measure_weighted_storage.py
streams_optimization-1.0.0.dev3.dist-info/DESCRIPTION.rst
streams_optimization-1.0.0.dev3.dist-info/METADATA
streams_optimization-1.0.0.dev3.dist-info/RECORD
streams_optimization-1.0.0.dev3.dist-info/WHEEL
streams_optimization-1.0.0.dev3.dist-info/metadata.json
streams_optimization-1.0.0.dev3.dist-info/top_level.txt
