Metadata-Version: 2.0
Name: streams-optimization
Version: 1.0.0.dev3
Summary: A library for LHCb trigger/stripping streams optimization
Home-page: https://gitlab.cern.ch/YSDA/streams-optimization/tree/master
Author: Yandex School of Data Analysis
Author-email: kazeevn@yandex-team.ru
License: Apache 2.0
Platform: UNKNOWN
Classifier: Development Status :: 4 - Beta
Classifier: Intended Audience :: Science/Research
Classifier: License :: OSI Approved :: Apache Software License
Classifier: Programming Language :: Python :: 2
Classifier: Topic :: System :: Clustering
Requires-Dist: ddt (==1.1.1)
Requires-Dist: lasagne (>=0.2.dev1)
Requires-Dist: numpy (>=1.12.0)
Requires-Dist: theano (>=0.9.0rc2)
